odoo/addons/fleet_vehicle_history_date_end/README.rst
odoo/addons/fleet_vehicle_history_date_end/__init__.py
odoo/addons/fleet_vehicle_history_date_end/__manifest__.py
odoo/addons/fleet_vehicle_history_date_end/models/__init__.py
odoo/addons/fleet_vehicle_history_date_end/models/fleet_vehicle_assignation_log.py
odoo/addons/fleet_vehicle_history_date_end/readme/CONTRIBUTORS.rst
odoo/addons/fleet_vehicle_history_date_end/readme/DESCRIPTION.rst
odoo/addons/fleet_vehicle_history_date_end/static/description/icon.png
odoo/addons/fleet_vehicle_history_date_end/static/description/index.html
odoo/addons/fleet_vehicle_history_date_end/tests/__init__.py
odoo/addons/fleet_vehicle_history_date_end/tests/test_vehicle_history_date_end.py
odoo12_addon_fleet_vehicle_history_date_end-12.0.1.0.0.dist-info/METADATA
odoo12_addon_fleet_vehicle_history_date_end-12.0.1.0.0.dist-info/WHEEL
odoo12_addon_fleet_vehicle_history_date_end-12.0.1.0.0.dist-info/top_level.txt
odoo12_addon_fleet_vehicle_history_date_end-12.0.1.0.0.dist-info/RECORD
